rle.cp37-win32.pyd
pyrdp/__init__.py
pyrdp/exceptions.py
pyrdp/bin/__init__.py
pyrdp/bin/clonecert.py
pyrdp/bin/convert.py
pyrdp/bin/mitm.py
pyrdp/bin/player.py
pyrdp/convert/Converter.py
pyrdp/convert/ExportedPDUStream.py
pyrdp/convert/JSONEventHandler.py
pyrdp/convert/MP4EventHandler.py
pyrdp/convert/PCAPConverter.py
pyrdp/convert/PCAPStream.py
pyrdp/convert/RDPReplayer.py
pyrdp/convert/ReplayConverter.py
pyrdp/convert/TLSPDUStream.py
pyrdp/convert/__init__.py
pyrdp/convert/pyrdp_scapy.py
pyrdp/convert/utils.py
pyrdp/core/FileProxy.py
pyrdp/core/__init__.py
pyrdp/core/ber.py
pyrdp/core/defer.py
pyrdp/core/event.py
pyrdp/core/helpers.py
pyrdp/core/mitm.py
pyrdp/core/observer.py
pyrdp/core/packing.py
pyrdp/core/per.py
pyrdp/core/sequencer.py
pyrdp/core/settings.py
pyrdp/core/ssl.py
pyrdp/core/stream.py
pyrdp/core/subject.py
pyrdp/core/timer.py
pyrdp/core/twisted.py
pyrdp/enum/__init__.py
pyrdp/enum/core.py
pyrdp/enum/gcc.py
pyrdp/enum/mcs.py
pyrdp/enum/negotiation.py
pyrdp/enum/ntlmssp.py
pyrdp/enum/orders.py
pyrdp/enum/player.py
pyrdp/enum/rdp.py
pyrdp/enum/scancode.py
pyrdp/enum/segmentation.py
pyrdp/enum/windows.py
pyrdp/enum/x224.py
pyrdp/enum/virtual_channel/__init__.py
pyrdp/enum/virtual_channel/clipboard.py
pyrdp/enum/virtual_channel/device_redirection.py
pyrdp/enum/virtual_channel/dynamic_channel.py
pyrdp/enum/virtual_channel/virtual_channel.py
pyrdp/layer/__init__.py
pyrdp/layer/buffered.py
pyrdp/layer/layer.py
pyrdp/layer/mcs.py
pyrdp/layer/player.py
pyrdp/layer/raw.py
pyrdp/layer/segmentation.py
pyrdp/layer/tcp.py
pyrdp/layer/tpkt.py
pyrdp/layer/x224.py
pyrdp/layer/rdp/__init__.py
pyrdp/layer/rdp/fastpath.py
pyrdp/layer/rdp/security.py
pyrdp/layer/rdp/slowpath.py
pyrdp/layer/rdp/virtual_channel/__init__.py
pyrdp/layer/rdp/virtual_channel/clipboard.py
pyrdp/layer/rdp/virtual_channel/device_redirection.py
pyrdp/layer/rdp/virtual_channel/dynamic_channel.py
pyrdp/layer/rdp/virtual_channel/virtual_channel.py
pyrdp/logging/StatCounter.py
pyrdp_mitm-2.1.0.dist-info/LICENSE
pyrdp_mitm-2.1.0.dist-info/METADATA
pyrdp_mitm-2.1.0.dist-info/WHEEL
pyrdp_mitm-2.1.0.dist-info/entry_points.txt
pyrdp_mitm-2.1.0.dist-info/top_level.txt
pyrdp_mitm-2.1.0.dist-info/RECORD
