Metadata-Version: 2.1
Name: pyrdp-mitm
Version: 2.1.0
Summary: Remote Desktop Protocol (RDP) Monster-in-the-Middle tool and Python library
Author: Émilio Gonzalez, Francis Labelle, Alexandre Beaulieu
Author-email: Olivier Bilodeau <obilodeau@gosecure.net>
Project-URL: Homepage, https://github.com/GoSecure/pyrdp
Keywords: RDP,MITM,interception,attack,pentest,honeypots
Classifier: Development Status :: 5 - Production/Stable
Classifier: Environment :: Console
Classifier: Environment :: X11 Applications :: Qt
Classifier: License :: OSI Approved :: GNU General Public License v3 or later (GPLv3+)
Classifier: Natural Language :: English
Classifier: Operating System :: POSIX
Classifier: Operating System :: Microsoft :: Windows
Classifier: Programming Language :: Python :: 3
Classifier: Programming Language :: Python :: 3.7
Classifier: Programming Language :: Python :: 3.8
Classifier: Programming Language :: Python :: 3.9
Classifier: Programming Language :: Python :: 3.10
Classifier: Programming Language :: Python :: 3.11
Classifier: Programming Language :: Python :: 3.12
Classifier: Topic :: Communications
Classifier: Topic :: Security
Classifier: Topic :: Software Development :: Libraries
Classifier: Topic :: Software Development :: Libraries :: Python Modules
Requires-Python: >=3.7
License-File: LICENSE
Requires-Dist: appdirs <2,>=1
Requires-Dist: cryptography <42,>=3.3.2
Requires-Dist: namesgenerator <1,>=0.3
Requires-Dist: progressbar2 <5,>=3.20
Requires-Dist: pyasn1 <1,>=0
Requires-Dist: pycryptodome <4,>=3.5
Requires-Dist: pyopenssl <24,>=19
Requires-Dist: pytz
Requires-Dist: rsa <5,>=4
Requires-Dist: scapy <3,>=2.4
Requires-Dist: service-identity >=18
Requires-Dist: twisted >=23
Provides-Extra: full
Requires-Dist: wheel >=0.34.2 ; extra == 'full'
Requires-Dist: av <12,>=8 ; extra == 'full'
Requires-Dist: PySide6 <7,>=6.3 ; extra == 'full'
Requires-Dist: qimage2ndarray <2,>=1.6 ; extra == 'full'
Requires-Dist: py-notifier >=0.5.0 ; extra == 'full'
Requires-Dist: WinToaster >=0.1.0 ; (platform_system == "Windows") and extra == 'full'
